[
  {
    "inputs": [
      {
        "internalType": "address",
        "name": "_owner",
        "type": "address"
      }
    ],
    "stateMutability": "nonpayable",
    "type": "constructor"
  },
  {
    "inputs": [],
    "name": "ReentrancyGuardReentrantCall",
    "type": "error"
  },
  {
    "inputs": [
      {
        "internalType": "address",
        "name": "token",
        "type": "address"
      }
    ],
    "name": "SafeERC20FailedOperation",
    "type": "error"
  },
  {
    "anonymous": false,
    "inputs": [
      {
        "indexed": false,
        "internalType": "uint256",
        "name": "amountSpent",
        "type": "uint256"
      },
      {
        "indexed": false,
        "internalType": "uint256",
        "name": "timestamp",
        "type": "uint256"
      }
    ],
    "name": "DCAExecuted",
    "type": "event"
  },
  {
    "anonymous": false,
    "inputs": [],
    "name": "VaultPaused",
    "type": "event"
  },
  {
    "anonymous": false,
    "inputs": [],
    "name": "VaultResumed",
    "type": "event"
  },
  {
    "anonymous": false,
    "inputs": [
      {
        "indexed": true,
        "internalType": "address",
        "name": "token",
        "type": "address"
      },
      {
        "indexed": false,
        "internalType": "uint256",
        "name": "amount",
        "type": "uint256"
      }
    ],
    "name": "Withdrawn",
    "type": "event"
  },
  {
    "inputs": [],
    "name": "active",
    "outputs": [
      {
        "internalType": "bool",
        "name": "",
        "type": "bool"
      }
    ],
    "stateMutability": "view",
    "type": "function"
  },
  {
    "inputs": [],
    "name": "buyAmount",
    "outputs": [
      {
        "internalType": "uint256",
        "name": "",
        "type": "uint256"
      }
    ],
    "stateMutability": "view",
    "type": "function"
  },
  {
    "inputs": [],
    "name": "canExecute",
    "outputs": [
      {
        "internalType": "bool",
        "name": "",
        "type": "bool"
      }
    ],
    "stateMutability": "view",
    "type": "function"
  },
  {
    "inputs": [],
    "name": "executeDCA",
    "outputs": [
      {
        "internalType": "bool",
        "name": "",
        "type": "bool"
      }
    ],
    "stateMutability": "nonpayable",
    "type": "function"
  },
  {
    "inputs": [],
    "name": "executionCount",
    "outputs": [
      {
        "internalType": "uint256",
        "name": "",
        "type": "uint256"
      }
    ],
    "stateMutability": "view",
    "type": "function"
  },
  {
    "inputs": [],
    "name": "factory",
    "outputs": [
      {
        "internalType": "address",
        "name": "",
        "type": "address"
      }
    ],
    "stateMutability": "view",
    "type": "function"
  },
  {
    "inputs": [],
    "name": "frequency",
    "outputs": [
      {
        "internalType": "uint256",
        "name": "",
        "type": "uint256"
      }
    ],
    "stateMutability": "view",
    "type": "function"
  },
  {
    "inputs": [],
    "name": "getStatus",
    "outputs": [
      {
        "internalType": "uint256",
        "name": "_buyAmount",
        "type": "uint256"
      },
      {
        "internalType": "uint256",
        "name": "_frequency",
        "type": "uint256"
      },
      {
        "internalType": "uint256",
        "name": "_lastExecution",
        "type": "uint256"
      },
      {
        "internalType": "uint256",
        "name": "_nextExecution",
        "type": "uint256"
      },
      {
        "internalType": "uint256",
        "name": "_totalInvested",
        "type": "uint256"
      },
      {
        "internalType": "uint256",
        "name": "_executionCount",
        "type": "uint256"
      },
      {
        "internalType": "bool",
        "name": "_active",
        "type": "bool"
      },
      {
        "internalType": "bool",
        "name": "_canExecute",
        "type": "bool"
      }
    ],
    "stateMutability": "view",
    "type": "function"
  },
  {
    "inputs": [
      {
        "internalType": "uint256",
        "name": "_buyAmount",
        "type": "uint256"
      },
      {
        "internalType": "uint256",
        "name": "_frequency",
        "type": "uint256"
      }
    ],
    "name": "initialize",
    "outputs": [],
    "stateMutability": "nonpayable",
    "type": "function"
  },
  {
    "inputs": [],
    "name": "lastExecution",
    "outputs": [
      {
        "internalType": "uint256",
        "name": "",
        "type": "uint256"
      }
    ],
    "stateMutability": "view",
    "type": "function"
  },
  {
    "inputs": [],
    "name": "owner",
    "outputs": [
      {
        "internalType": "address",
        "name": "",
        "type": "address"
      }
    ],
    "stateMutability": "view",
    "type": "function"
  },
  {
    "inputs": [],
    "name": "pause",
    "outputs": [],
    "stateMutability": "nonpayable",
    "type": "function"
  },
  {
    "inputs": [],
    "name": "resume",
    "outputs": [],
    "stateMutability": "nonpayable",
    "type": "function"
  },
  {
    "inputs": [],
    "name": "totalInvested",
    "outputs": [
      {
        "internalType": "uint256",
        "name": "",
        "type": "uint256"
      }
    ],
    "stateMutability": "view",
    "type": "function"
  },
  {
    "inputs": [
      {
        "internalType": "uint256",
        "name": "_buyAmount",
        "type": "uint256"
      },
      {
        "internalType": "uint256",
        "name": "_frequency",
        "type": "uint256"
      }
    ],
    "name": "updateSettings",
    "outputs": [],
    "stateMutability": "nonpayable",
    "type": "function"
  },
  {
    "inputs": [
      {
        "internalType": "address",
        "name": "token",
        "type": "address"
      },
      {
        "internalType": "uint256",
        "name": "amount",
        "type": "uint256"
      }
    ],
    "name": "withdraw",
    "outputs": [],
    "stateMutability": "nonpayable",
    "type": "function"
  },
  {
    "inputs": [
      {
        "internalType": "uint256",
        "name": "amount",
        "type": "uint256"
      }
    ],
    "name": "withdrawAVAX",
    "outputs": [],
    "stateMutability": "nonpayable",
    "type": "function"
  },
  {
    "stateMutability": "payable",
    "type": "receive"
  }
]
